py2jn/__init__.py
py2jn/__main__.py
py2jn/reader.py
py2jn/tools.py
py2jn-0.0.2.dist-info/LICENSE
py2jn-0.0.2.dist-info/METADATA
py2jn-0.0.2.dist-info/WHEEL
py2jn-0.0.2.dist-info/top_level.txt
py2jn-0.0.2.dist-info/zip-safe
py2jn-0.0.2.dist-info/RECORD
